frisknstech.py
frisknstech1.py
frisk_nstech-2.1.dist-info/METADATA
frisk_nstech-2.1.dist-info/WHEEL
frisk_nstech-2.1.dist-info/licenses/LICENSE
frisk_nstech-2.1.dist-info/RECORD
